{
  "projects":[

    {
      "title":"MyGoPandai Learning Platform",
      "description":"ASP.NET learning platform with instructor and guest modules.",
      "skills":["html","css","database"],
      "github":"#"
    },

    {
      "title":"Flight Reservation System",
      "description":"C++ system implementing arrays and linked lists.",
      "skills":["cplusplus"],
      "github":"#"
    },

    {
      "title":"Airport Concurrency Simulation",
      "description":"Java concurrency system with threads and locks.",
      "skills":["java"],
      "github":"#"
    },

    {
      "title":"Data Mining Model",
      "description":"Predictive modeling using SAS Viya.",
      "skills":["analytics"],
      "github":"#"
    }

  ]
}